django_acdhch_functions/.gitignore
django_acdhch_functions/__init__.py
django_acdhch_functions/templates/acdhch_functions/imprint.html
django_acdhch_functions/templates/base.html
django_acdhch_functions/templates/matomo.html
django_acdhch_functions/templatetags/django_acdhch_functions.py
django_acdhch_functions/urls.py
django_acdhch_functions/utils.py
django_acdhch_functions/views.py
django_acdhch_functions-0.1.4.dist-info/METADATA
django_acdhch_functions-0.1.4.dist-info/WHEEL
django_acdhch_functions-0.1.4.dist-info/RECORD
