Metadata-Version: 2.1
Name: django-acdhch-functions
Version: 0.1.4
Summary: 
Author: Birger Schacht
Author-email: birger.schacht@oeaw.ac.at
Requires-Python: >=3.11,<4.0
Classifier: Programming Language :: Python :: 3
Classifier: Programming Language :: Python :: 3.11
Classifier: Programming Language :: Python :: 3.12
Requires-Dist: django (>=4.1)
